read_toml/__init__.py
read_toml/_impl.py
read_toml/py.typed
read_toml-0.0.0a0.dist-info/LICENSE
read_toml-0.0.0a0.dist-info/WHEEL
read_toml-0.0.0a0.dist-info/METADATA
read_toml-0.0.0a0.dist-info/RECORD
